COPYRIGHT
MANIFEST.in
README.txt
setup.cfg
setup.py
docs/index.txt
docs/installation.txt
docs/rdflib.txt
docs/sqlalchemy.txt
virtuoso/__init__.py
virtuoso/alchemy.py
virtuoso/common.py
virtuoso/vsparql.py
virtuoso/vstore.py
virtuoso.egg-info/PKG-INFO
virtuoso.egg-info/SOURCES.txt
virtuoso.egg-info/dependency_links.txt
virtuoso.egg-info/entry_points.txt
virtuoso.egg-info/not-zip-safe
virtuoso.egg-info/requires.txt
virtuoso.egg-info/top_level.txt
virtuoso/tests/test_rdflib3.py
virtuoso/tests/test_sqlalchemy.py
virtuoso/tests/test_virtuoso.py