Metadata-Version: 1.0
Name: virtuoso
Version: 0.10.7
Summary: OpenLink Virtuoso Support for SQLAlchemy and RDFLib
Home-page: http://packages.python.org/virtuoso
Author: Open Knowledge Foundation
Author-email: okfn-help@okfn.org
License: BSD
Platform: UNKNOWN
